mmhuman3d/__init__.py
mmhuman3d/version.py
mmhuman3d/apis/__init__.py
mmhuman3d/apis/inference.py
mmhuman3d/apis/test.py
mmhuman3d/apis/train.py
mmhuman3d/core/__init__.py
mmhuman3d/core/distributed_wrapper.py
mmhuman3d/core/cameras/__init__.py
mmhuman3d/core/cameras/builder.py
mmhuman3d/core/cameras/camera_parameters.py
mmhuman3d/core/cameras/cameras.py
mmhuman3d/core/conventions/__init__.py
mmhuman3d/core/conventions/cameras/__init__.py
mmhuman3d/core/conventions/cameras/convert_convention.py
mmhuman3d/core/conventions/cameras/convert_projection.py
mmhuman3d/core/conventions/joints_mapping/__init__.py
mmhuman3d/core/conventions/joints_mapping/standard_joint_angles.py
mmhuman3d/core/conventions/keypoints_mapping/__init__.py
mmhuman3d/core/conventions/keypoints_mapping/agora.py
mmhuman3d/core/conventions/keypoints_mapping/coco.py
mmhuman3d/core/conventions/keypoints_mapping/coco_wholebody.py
mmhuman3d/core/conventions/keypoints_mapping/crowdpose.py
mmhuman3d/core/conventions/keypoints_mapping/face3d.py
mmhuman3d/core/conventions/keypoints_mapping/flame.py
mmhuman3d/core/conventions/keypoints_mapping/gta.py
mmhuman3d/core/conventions/keypoints_mapping/h36m.py
mmhuman3d/core/conventions/keypoints_mapping/human_data.py
mmhuman3d/core/conventions/keypoints_mapping/hybrik.py
mmhuman3d/core/conventions/keypoints_mapping/instavariety.py
mmhuman3d/core/conventions/keypoints_mapping/lsp.py
mmhuman3d/core/conventions/keypoints_mapping/mano.py
mmhuman3d/core/conventions/keypoints_mapping/mediapipe.py
mmhuman3d/core/conventions/keypoints_mapping/mpi_inf_3dhp.py
mmhuman3d/core/conventions/keypoints_mapping/mpii.py
mmhuman3d/core/conventions/keypoints_mapping/openpose.py
mmhuman3d/core/conventions/keypoints_mapping/penn_action.py
mmhuman3d/core/conventions/keypoints_mapping/posetrack.py
mmhuman3d/core/conventions/keypoints_mapping/pw3d.py
mmhuman3d/core/conventions/keypoints_mapping/pymafx_smplx.py
mmhuman3d/core/conventions/keypoints_mapping/smpl.py
mmhuman3d-0.11.0.dist-info/LICENSE
mmhuman3d-0.11.0.dist-info/METADATA
mmhuman3d-0.11.0.dist-info/WHEEL
mmhuman3d-0.11.0.dist-info/top_level.txt
mmhuman3d-0.11.0.dist-info/RECORD
