Metadata-Version: 2.1
Name: mmhuman3d
Version: 0.11.0
Summary: OpenMMLab 3D Human Parametric Model Toolbox and Benchmark
Home-page: https://github.com/open-mmlab/mmhuman3d
Author: OpenMMLab
Author-email: openmmlab@gmail.com
License: Apache License 2.0
Keywords: 3D Human
Platform: UNKNOWN
Classifier: Development Status :: 4 - Beta
Classifier: License :: OSI Approved :: Apache Software License
Classifier: Operating System :: OS Independent
Classifier: Programming Language :: Python :: 3
Classifier: Programming Language :: Python :: 3.6
Classifier: Programming Language :: Python :: 3.7
Classifier: Programming Language :: Python :: 3.8
Classifier: Programming Language :: Python :: 3.9
Requires-Dist: astropy
Requires-Dist: cdflib (<0.4.0)
Requires-Dist: chumpy
Requires-Dist: colormap
Requires-Dist: easydev
Requires-Dist: einops
Requires-Dist: h5py
Requires-Dist: matplotlib
Requires-Dist: numpy
Requires-Dist: opencv-python
Requires-Dist: pandas (<2.0.0)
Requires-Dist: pickle5
Requires-Dist: plyfile
Requires-Dist: rtree
Requires-Dist: scikit-image
Requires-Dist: scipy
Requires-Dist: smplx
Requires-Dist: tqdm
Requires-Dist: trimesh
Requires-Dist: vedo
